fastv2ray/__init__.py
fastv2ray/app.py
fastv2ray/bins/geoip-only-cn-private.dat
fastv2ray/bins/geoip.dat
fastv2ray/bins/geosite.dat
fastv2ray/bins/v2ctl
fastv2ray/bins/v2ray
fastv2ray/configs/default.json
fastv2ray-0.0.2.dist-info/METADATA
fastv2ray-0.0.2.dist-info/WHEEL
fastv2ray-0.0.2.dist-info/entry_points.txt
fastv2ray-0.0.2.dist-info/top_level.txt
fastv2ray-0.0.2.dist-info/RECORD
