Metadata-Version: 2.1
Name: fastv2ray
Version: 0.0.2
Summary: NULL
Home-page: https://google.com
Author: slipper
Author-email: r2fscg@gmail.com
License: UNKNOWN
Platform: UNKNOWN
Classifier: Programming Language :: Python :: 3
Classifier: License :: OSI Approved :: MIT License
Classifier: Operating System :: OS Independent
Requires-Dist: codefast
Requires-Dist: fire
Requires-Dist: simauth
Requires-Dist: asyncio
